iterm2_focus/__init__.py
iterm2_focus/cli.py
iterm2_focus/focus.py
iterm2_focus/py.typed
iterm2_focus/utils.py
iterm2_focus/mcp/__init__.py
iterm2_focus/mcp/__main__.py
iterm2_focus/mcp/server.py
iterm2_focus/mcp/tools/__init__.py
iterm2_focus/mcp/tools/iterm_tools.py
iterm2_focus-0.0.11.dist-info/METADATA
iterm2_focus-0.0.11.dist-info/WHEEL
iterm2_focus-0.0.11.dist-info/entry_points.txt
iterm2_focus-0.0.11.dist-info/licenses/LICENSE
iterm2_focus-0.0.11.dist-info/RECORD
