Metadata-Version: 2.2
Name: iterm2-focus
Version: 0.0.11
Summary: Focus iTerm2 sessions by ID
Project-URL: Homepage, https://github.com/mkusaka/iterm2-focus
Project-URL: Bug Tracker, https://github.com/mkusaka/iterm2-focus/issues
Project-URL: Documentation, https://github.com/mkusaka/iterm2-focus#readme
Project-URL: Source Code, https://github.com/mkusaka/iterm2-focus
Author-email: mkusaka <hinoshita1992@gmail.com>
License: MIT
License-File: LICENSE
Keywords: cli,focus,iterm2,macos,terminal
Classifier: Development Status :: 4 - Beta
Classifier: Environment :: Console
Classifier: Environment :: MacOS X
Classifier: Intended Audience :: Developers
Classifier: License :: OSI Approved :: MIT License
Classifier: Operating System :: MacOS
Classifier: Programming Language :: Python :: 3
Classifier: Programming Language :: Python :: 3.10
Classifier: Programming Language :: Python :: 3.11
Classifier: Programming Language :: Python :: 3.12
Classifier: Programming Language :: Python :: 3.13
Classifier: Topic :: Terminals
Classifier: Topic :: Utilities
Classifier: Typing :: Typed
Requires-Python: >=3.10
Requires-Dist: click>=8.1.0
Requires-Dist: iterm2>=2.7
Provides-Extra: dev
Requires-Dist: black>=23.0.0; extra == 'dev'
Requires-Dist: mypy>=1.5.0; extra == 'dev'
Requires-Dist: pytest-asyncio>=0.21.0; extra == 'dev'
Requires-Dist: pytest-cov>=4.1.0; extra == 'dev'
Requires-Dist: pytest-mock>=3.11.0; extra == 'dev'
Requires-Dist: pytest>=7.4.0; extra == 'dev'
Requires-Dist: ruff>=0.1.0; extra == 'dev'
Requires-Dist: twine>=5.0.0; extra == 'dev'
Requires-Dist: types-click>=7.1.0; extra == 'dev'
Provides-Extra: mcp
Requires-Dist: mcp[cli]>=1.0.0; extra == 'mcp'
Requires-Dist: pydantic>=2.0.0; extra == 'mcp'
